{
  "To Do": [
    {
      "title": "Card 2",
      "metadata": {
        "id": "2ab11732-7211-4276-bac8-23909e453005",
        "title": "Card 2",
        "notes": "",
        "tags": [],
        "color": null,
        "links": []
      }
    },
    {
      "title": "Card 1",
      "metadata": {
        "id": "d883595c-cc07-4e6b-8c32-5398fb68ded9",
        "title": "Card 1",
        "notes": "",
        "tags": [],
        "color": null,
        "links": []
      }
    }
  ],
  "In Progress": [
    {
      "title": "Move Me",
      "metadata": {
        "id": "fb3bf05a-3f45-4b26-91e7-875face34084",
        "title": "Move Me",
        "notes": "",
        "tags": [],
        "color": null,
        "links": []
      }
    }
  ],
  "Done": []
}